streamingxmlwriter/__init__.py
streamingxmlwriter/core.py
streamingxmlwriter-1.0.0.dist-info/DESCRIPTION.rst
streamingxmlwriter-1.0.0.dist-info/METADATA
streamingxmlwriter-1.0.0.dist-info/RECORD
streamingxmlwriter-1.0.0.dist-info/WHEEL
streamingxmlwriter-1.0.0.dist-info/metadata.json
streamingxmlwriter-1.0.0.dist-info/top_level.txt
