Metadata-Version: 2.0
Name: streamingxmlwriter
Version: 1.0.0
Summary: A lightweight pythonic standard compliant streaming xml writer
Home-page: http://github.com/acsone/streamingxmlwriter
Author: ACSONE SA/NV
Author-email: info@acsone.eu
License: LGPLv3
Platform: UNKNOWN
Classifier: Development Status :: 5 - Production/Stable
Classifier: Intended Audience :: Developers
Classifier: License :: OSI Approved :: GNU Lesser General Public License v3 (LGPLv3)
Classifier: Operating System :: OS Independent
Classifier: Programming Language :: Python
Requires-Dist: six
